marshmallow_polyfield/__init__.py
marshmallow_polyfield/polyfield.py
marshmallow_polyfield-5.10.dist-info/LICENSE
marshmallow_polyfield-5.10.dist-info/METADATA
marshmallow_polyfield-5.10.dist-info/WHEEL
marshmallow_polyfield-5.10.dist-info/top_level.txt
marshmallow_polyfield-5.10.dist-info/RECORD
