Metadata-Version: 2.1
Name: marshmallow-polyfield
Version: 5.10
Summary: An unofficial extension to Marshmallow to allow for polymorphic fields
Home-page: https://github.com/Bachmann1234/marshmallow-polyfield
Author: Matt Bachmann
Author-email: bachmann.matt@gmail.com
License: Apache 2.0
Keywords: serialization,rest,json,api,marshal,marshalling,deserialization,validation,schema
Platform: UNKNOWN
Classifier: Intended Audience :: Developers
Classifier: License :: OSI Approved :: Apache Software License
Classifier: Programming Language :: Python :: 3
Classifier: Programming Language :: Python :: 3.6
Classifier: Programming Language :: Python :: 3.7
Classifier: Programming Language :: Python :: Implementation :: CPython
Classifier: Programming Language :: Python :: Implementation :: PyPy
Requires-Python: >=3.5
